pyfiglet/__init__.py
pyfiglet/__main__.py
pyfiglet/test.py
pyfiglet/version.py
pyfiglet/fonts/1943____.flf
pyfiglet/fonts/1row.flf
pyfiglet/fonts/3-d.flf
pyfiglet/fonts/3d-ascii.flf
pyfiglet/fonts/3d_diagonal.flf
pyfiglet/fonts/3x5.flf
pyfiglet/fonts/4max.flf
pyfiglet/fonts/4x4_offr.flf
pyfiglet/fonts/5lineoblique.flf
pyfiglet/fonts/5x7.flf
pyfiglet/fonts/5x8.flf
pyfiglet/fonts/64f1____.flf
pyfiglet/fonts/6x10.flf
pyfiglet/fonts/6x9.flf
pyfiglet/fonts/__init__.py
pyfiglet/fonts/a_zooloo.flf
pyfiglet/fonts/acrobatic.flf
pyfiglet/fonts/advenger.flf
pyfiglet/fonts/alligator.flf
pyfiglet/fonts/alligator2.flf
pyfiglet/fonts/alpha.flf
pyfiglet/fonts/alphabet.flf
pyfiglet/fonts/amc_3_line.flf
pyfiglet/fonts/amc_3_liv1.flf
pyfiglet/fonts/amc_aaa01.flf
pyfiglet/fonts/amc_neko.flf
pyfiglet/fonts/amc_razor.flf
pyfiglet/fonts/amc_razor2.flf
pyfiglet/fonts/amc_slash.flf
pyfiglet/fonts/amc_slider.flf
pyfiglet/fonts/amc_thin.flf
pyfiglet/fonts/amc_tubes.flf
pyfiglet/fonts/amc_untitled.flf
pyfiglet/fonts/ansi_regular.flf
pyfiglet/fonts/ansi_shadow.flf
pyfiglet/fonts/aquaplan.flf
pyfiglet/fonts/arrows.flf
pyfiglet/fonts/asc_____.flf
pyfiglet/fonts/ascii___.flf
pyfiglet/fonts/ascii_new_roman.flf
pyfiglet/fonts/assalt_m.flf
pyfiglet/fonts/asslt__m.flf
pyfiglet/fonts/atc_____.flf
pyfiglet/fonts/atc_gran.flf
pyfiglet/fonts/avatar.flf
pyfiglet/fonts/b1ff.flf
pyfiglet/fonts/b_m__200.flf
pyfiglet/fonts/banner.flf
pyfiglet/fonts/banner3-D.flf
pyfiglet/fonts/banner3.flf
pyfiglet/fonts/banner4.flf
pyfiglet/fonts/barbwire.flf
pyfiglet/fonts/basic.flf
pyfiglet/fonts/battle_s.flf
pyfiglet/fonts/battlesh.flf
pyfiglet/fonts/baz__bil.flf
pyfiglet/fonts/bear.flf
pyfiglet/fonts/beer_pub.flf
pyfiglet/fonts/bell.flf
pyfiglet/fonts/benjamin.flf
pyfiglet/fonts/big.flf
pyfiglet/fonts/big_money-ne.flf
pyfiglet/fonts/big_money-nw.flf
pyfiglet/fonts/big_money-se.flf
pyfiglet/fonts/big_money-sw.flf
pyfiglet/fonts/bigchief.flf
pyfiglet/fonts/bigfig.flf
pyfiglet/fonts/binary.flf
pyfiglet/fonts/block.flf
pyfiglet-1.0.1.dist-info/LICENSE
pyfiglet-1.0.1.dist-info/METADATA
pyfiglet-1.0.1.dist-info/WHEEL
pyfiglet-1.0.1.dist-info/entry_points.txt
pyfiglet-1.0.1.dist-info/top_level.txt
pyfiglet-1.0.1.dist-info/RECORD
