Metadata-Version: 2.1
Name: pyfiglet
Version: 1.0.1
Summary: Pure-python FIGlet implementation
Home-page: https://github.com/pwaller/pyfiglet
Author: Peter Waller (Thanks to Christopher Jones and Stefano Rivera)
Author-email: p@pwaller.net
License: MIT
Classifier: Development Status :: 5 - Production/Stable
Classifier: Environment :: Console
Classifier: Intended Audience :: Developers
Classifier: License :: OSI Approved :: MIT License
Classifier: Natural Language :: English
Classifier: Natural Language :: Japanese
Classifier: Natural Language :: Bulgarian
Classifier: Natural Language :: Bosnian
Classifier: Natural Language :: Macedonian
Classifier: Natural Language :: Russian
Classifier: Natural Language :: Serbian
Classifier: Operating System :: Unix
Classifier: Programming Language :: Python
Classifier: Programming Language :: Python :: 3
Classifier: Programming Language :: Python :: 3.7
Classifier: Programming Language :: Python :: 3.8
Classifier: Programming Language :: Python :: 3.9
Classifier: Programming Language :: Python :: 3.10
Classifier: Programming Language :: Python :: 3.11
Classifier: Topic :: Text Processing
Classifier: Topic :: Text Processing :: Fonts
Requires-Python: >=3.9
License-File: LICENSE
